MANIFEST.in
README.rst
requirements.txt
setup.cfg
setup.py
gotenshita/__init__.py
gotenshita.egg-info/PKG-INFO
gotenshita.egg-info/SOURCES.txt
gotenshita.egg-info/dependency_links.txt
gotenshita.egg-info/entry_points.txt
gotenshita.egg-info/requires.txt
gotenshita.egg-info/top_level.txt