Metadata-Version: 1.1
Name: gotenshita
Version: 2.2.4
Summary: Gotenshita notifier.
Home-page: http://github.com/wkentaro/gotenshita
Author: Kentaro Wada
Author-email: www.kentaro.wada@gmail.com
License: MIT
Keywords: utility
Platform: UNKNOWN
Classifier: Development Status :: 5 - Production/Stable
Classifier: Intended Audience :: Developers
Classifier: License :: OSI Approved :: MIT License
Classifier: Operating System :: POSIX
Classifier: Topic :: Internet :: WWW/HTTP
